odoo/addons/website_event_filter_organizer/README.rst
odoo/addons/website_event_filter_organizer/__init__.py
odoo/addons/website_event_filter_organizer/__manifest__.py
odoo/addons/website_event_filter_organizer/controllers/__init__.py
odoo/addons/website_event_filter_organizer/controllers/main.py
odoo/addons/website_event_filter_organizer/demo/assets.xml
odoo/addons/website_event_filter_organizer/i18n/de.po
odoo/addons/website_event_filter_organizer/i18n/es.po
odoo/addons/website_event_filter_organizer/i18n/it.po
odoo/addons/website_event_filter_organizer/i18n/pt_BR.po
odoo/addons/website_event_filter_organizer/i18n/sl.po
odoo/addons/website_event_filter_organizer/i18n/website_event_filter_organizer.pot
odoo/addons/website_event_filter_organizer/readme/CONTRIBUTORS.rst
odoo/addons/website_event_filter_organizer/readme/DESCRIPTION.rst
odoo/addons/website_event_filter_organizer/readme/USAGE.rst
odoo/addons/website_event_filter_organizer/static/description/icon.png
odoo/addons/website_event_filter_organizer/static/description/index.html
odoo/addons/website_event_filter_organizer/static/src/js/tour.js
odoo/addons/website_event_filter_organizer/tests/__init__.py
odoo/addons/website_event_filter_organizer/tests/test_ui.py
odoo/addons/website_event_filter_organizer/views/website_event.xml
odoo12_addon_website_event_filter_organizer-12.0.1.0.0.99.dev7.dist-info/METADATA
odoo12_addon_website_event_filter_organizer-12.0.1.0.0.99.dev7.dist-info/WHEEL
odoo12_addon_website_event_filter_organizer-12.0.1.0.0.99.dev7.dist-info/top_level.txt
odoo12_addon_website_event_filter_organizer-12.0.1.0.0.99.dev7.dist-info/RECORD
